p1/__init__.py
p1/cli.py
p1/operations.py
django_calcul-0.3.1.dist-info/METADATA
django_calcul-0.3.1.dist-info/WHEEL
django_calcul-0.3.1.dist-info/entry_points.txt
django_calcul-0.3.1.dist-info/top_level.txt
django_calcul-0.3.1.dist-info/RECORD
