Metadata-Version: 2.4
Name: django-calcul
Version: 0.3.1
Author: Nicosidick
Author-email: abou210traore@gmail.com
License: MIT
Classifier: Programming Language :: Python :: 3
Classifier: Framework :: Django
Classifier: License :: OSI Approved :: MIT License
Dynamic: author
Dynamic: author-email
Dynamic: classifier
Dynamic: description
Dynamic: description-content-type
Dynamic: license
